{
    "c3ef_1-3": {
        "id": "c3ef_1-3",
        "multiplier": 1,
        "param_name": "accumulated_charged_electric_quantity",
        "pgn": "c3ef",
        "range": "0 to 20000000",
        "start_position": 1.3,
        "taip_tag": "ZQ.12",
        "taip_units": "kwh",
        "units": "kwh",
        "xaem_bit": 27,
        "xaem_group": 3
    },
    "c3ef_4-6": {
        "id": "c3ef_4-6",
        "multiplier": 1,
        "param_name": "accumulated_discharged_electric_quantity",
        "pgn": "c3ef",
        "range": "0 to 20000000",
        "start_position": 4.6,
        "taip_tag": "ZQ.13",
        "taip_units": "kwh",
        "units": "kwh",
        "xaem_bit": 28,
        "xaem_group": 3
    },
    "c3ef_7-8": {
        "id": "c3ef_7-8",
        "multiplier": 0.1,
        "param_name": "single_charged_electric_quantity",
        "pgn": "c3ef",
        "range": "0 to 6554",
        "start_position": 7.8,
        "taip_tag": "ZQ.14",
        "taip_units": "kwh",
        "units": "kwh",
        "xaem_bit": 29,
        "xaem_group": 3
    }
}
